dbtc/__init__.py
dbtc/_version.py
dbtc/cli.py
dbtc/console.py
dbtc/utils.py
dbtc/client/__init__.py
dbtc/client/admin.py
dbtc/client/base.py
dbtc/client/main.py
dbtc/client/metadata.py
dbtc/client/semantic_layer.py
dbtc/models/__init__.py
dbtc/models/semantic_layer.py
dbtc/models/webhooks.py
dbtc-0.11.7.dist-info/METADATA
dbtc-0.11.7.dist-info/WHEEL
dbtc-0.11.7.dist-info/entry_points.txt
dbtc-0.11.7.dist-info/RECORD
