Metadata-Version: 2.4
Name: dbtc
Version: 0.11.7
Summary: An unaffiliated python wrapper for dbt Cloud APIs
Author-email: Doug Guthrie <douglas.p.guthrie@gmail.com>
License-Expression: MIT
Keywords: API,dbt,dbt Cloud,requests
Requires-Python: >=3.8
Requires-Dist: pandas<2.2.0
Requires-Dist: pyarrow>=15.0.0
Requires-Dist: pydantic>=2.5.3
Requires-Dist: requests>=2.27.1
Requires-Dist: typer[all]>=0.9.0
